{
  "data": {
    "repository": {
      "url": "https://github.com/wmde/wikibase-rest-api-proposal",
      "name": "wikibase-rest-api-proposal",
      "nameWithOwner": "wmde/wikibase-rest-api-proposal",
      "description": "A schema proposal for the future Wikibase REST API.",
      "descriptionHTML": "<div>A schema proposal for the future Wikibase REST API.</div>",
      "primaryLanguage": {
        "name": "JavaScript"
      },
      "languages": {
        "nodes": [
          {
            "name": "JavaScript"
          }
        ]
      },
      "defaultBranchRef": {
        "target": {
          "tree": {
            "entries": [
              {
                "name": ".github"
              },
              {
                "name": ".gitignore"
              },
              {
                "name": "DECISION-RESEARCH.md"
              },
              {
                "name": "GOTCHAS.md"
              },
              {
                "name": "LICENSE"
              },
              {
                "name": "PRINCIPLES.md"
              },
              {
                "name": "README.md"
              },
              {
                "name": "SCOPE.md"
              },
              {
                "name": "docs"
              },
              {
                "name": "loaders"
              },
              {
                "name": "package-lock.json"
              },
              {
                "name": "package.json"
              },
              {
                "name": "specs"
              }
            ]
          }
        }
      }
    }
  }
}
